MANIFEST.in
README.rst
setup.py
django_simple_multilingual_survey.egg-info/PKG-INFO
django_simple_multilingual_survey.egg-info/SOURCES.txt
django_simple_multilingual_survey.egg-info/dependency_links.txt
django_simple_multilingual_survey.egg-info/requires.txt
django_simple_multilingual_survey.egg-info/top_level.txt
multilingual_survey/__init__.py
multilingual_survey/admin.py
multilingual_survey/forms.py
multilingual_survey/managers.py
multilingual_survey/models.py
multilingual_survey/tests.py
multilingual_survey/urls.py
multilingual_survey/views.py
multilingual_survey/templates/admin/hvad/change_form.html
multilingual_survey/templates/admin/hvad/deletion_not_allowed.html
multilingual_survey/templates/admin/hvad/edit_inline/stacked.html
multilingual_survey/templates/admin/hvad/edit_inline/tabular.html
multilingual_survey/templates/admin/hvad/includes/translation_tabs.html
multilingual_survey/templates/multilingual_survey/form.html
multilingual_survey/templates/multilingual_survey/success.html
multilingual_survey/templates/multilingual_survey/survey.html
multilingual_survey/templatetags/__init__.py
multilingual_survey/templatetags/survey.py