Metadata-Version: 1.1
Name: django-simple-multilingual-survey
Version: 0.1.2
Summary: A simple Django app to conduct Web-based multilingual surveys.
Home-page: https://github.com/diadzine/django-simple-multilingual-survey
Author: Aymeric Bringard
Author-email: diadzine@gmail.com
License: BSD License
Platform: UNKNOWN
Classifier: Environment :: Web Environment
Classifier: Framework :: Django
Classifier: Intended Audience :: Developers
Classifier: License :: OSI Approved :: BSD License
Classifier: Natural Language :: English
Classifier: Operating System :: OS Independent
Classifier: Programming Language :: Python
Classifier: Programming Language :: Python :: 2.6
Classifier: Programming Language :: Python :: 2.7
Classifier: Topic :: Internet :: WWW/HTTP
Classifier: Topic :: Internet :: WWW/HTTP :: Dynamic Content
